<?xml version="1.0" encoding="UTF-8"?>
<DataCompositionSchema xmlns="http://v8.1c.ru/8.1/data-composition-system/schema" xmlns:dcscom="http://v8.1c.ru/8.1/data-composition-system/common" xmlns:dcscor="http://v8.1c.ru/8.1/data-composition-system/core" xmlns:dcsset="http://v8.1c.ru/8.1/data-composition-system/settings" xmlns:v8="http://v8.1c.ru/8.1/data/core" xmlns:v8ui="http://v8.1c.ru/8.1/data/ui" xmlns:xs="http://www.w3.org/2001/XMLSchema" xmlns:xsi="http://www.w3.org/2001/XMLSchema-instance">
	<dataSource>
		<name>ИсточникДанных1</name>
		<dataSourceType>Local</dataSourceType>
	</dataSource>
	<dataSet xsi:type="DataSetUnion">
		<name>ДанныеРесурсы</name>
		<field xsi:type="DataSetFieldField">
			<dataPath>Ресурс.ЕдиницаИзмерения</dataPath>
			<field>Ресурс.ЕдиницаИзмерения</field>
			<title xsi:type="v8:LocalStringType">
				<v8:item>
					<v8:lang>ru</v8:lang>
					<v8:content>Ед.изм.</v8:content>
				</v8:item>
			</title>
		</field>
		<field xsi:type="DataSetFieldField">
			<dataPath>Ресурс</dataPath>
			<field>Ресурс</field>
			<title xsi:type="v8:LocalStringType">
				<v8:item>
					<v8:lang>ru</v8:lang>
					<v8:content>Трудовые ресурсы</v8:content>
				</v8:item>
			</title>
			<role>
				<dcscom:dimension>true</dcscom:dimension>
			</role>
			<inputParameters>
				<dcscor:item>
					<dcscor:parameter>ПараметрыВыбора</dcscor:parameter>
					<dcscor:value xsi:type="dcscor:ChoiceParameters">
						<dcscor:item>
							<dcscor:choiceParameter>Отбор.ИНАГРО_ТипРесурсов</dcscor:choiceParameter>
							<dcscor:value xsi:type="dcscor:DesignTimeValue">Перечисление.ИНАГРО_ТипыРесурсов.ТрудовыеРесурсы</dcscor:value>
						</dcscor:item>
					</dcscor:value>
				</dcscor:item>
			</inputParameters>
		</field>
		<field xsi:type="DataSetFieldField">
			<dataPath>КлючСтроки</dataPath>
			<field>КлючСтроки</field>
			<title xsi:type="v8:LocalStringType">
				<v8:item>
					<v8:lang>ru</v8:lang>
					<v8:content>Код работы</v8:content>
				</v8:item>
			</title>
			<role>
				<dcscom:dimension>true</dcscom:dimension>
			</role>
			<appearance>
				<dcscor:item xsi:type="dcsset:SettingsParameterValue">
					<dcscor:use>false</dcscor:use>
					<dcscor:parameter>МаксимальнаяШирина</dcscor:parameter>
					<dcscor:value xsi:type="xs:decimal">10</dcscor:value>
				</dcscor:item>
			</appearance>
		</field>
		<field xsi:type="DataSetFieldField">
			<dataPath>Период</dataPath>
			<field>Период</field>
			<title xsi:type="v8:LocalStringType">
				<v8:item>
					<v8:lang>ru</v8:lang>
					<v8:content>Период</v8:content>
				</v8:item>
			</title>
			<appearance>
				<dcscor:item xsi:type="dcsset:SettingsParameterValue">
					<dcscor:parameter>ГоризонтальноеПоложение</dcscor:parameter>
					<dcscor:value xsi:type="v8ui:HorizontalAlign">Center</dcscor:value>
				</dcscor:item>
			</appearance>
		</field>
		<field xsi:type="DataSetFieldField">
			<dataPath>КоличествоПлан</dataPath>
			<field>КоличествоПлан</field>
			<title xsi:type="v8:LocalStringType">
				<v8:item>
					<v8:lang>ru</v8:lang>
					<v8:content>Количество план</v8:content>
				</v8:item>
			</title>
		</field>
		<field xsi:type="DataSetFieldField">
			<dataPath>КоличествоФакт</dataPath>
			<field>КоличествоФакт</field>
			<title xsi:type="v8:LocalStringType">
				<v8:item>
					<v8:lang>ru</v8:lang>
					<v8:content>Количество факт</v8:content>
				</v8:item>
			</title>
		</field>
		<field xsi:type="DataSetFieldField">
			<dataPath>СуммаФакт</dataPath>
			<field>СуммаФакт</field>
			<title xsi:type="v8:LocalStringType">
				<v8:item>
					<v8:lang>ru</v8:lang>
					<v8:content>Сумма факт</v8:content>
				</v8:item>
			</title>
		</field>
		<field xsi:type="DataSetFieldField">
			<dataPath>Регистратор</dataPath>
			<field>Регистратор</field>
			<role>
				<dcscom:periodNumber>1</dcscom:periodNumber>
				<dcscom:periodType>Main</dcscom:periodType>
			</role>
		</field>
		<field xsi:type="DataSetFieldField">
			<dataPath>ПериодГод</dataPath>
			<field>ПериодГод</field>
			<role>
				<dcscom:periodNumber>2</dcscom:periodNumber>
				<dcscom:periodType>Additional</dcscom:periodType>
			</role>
			<appearance>
				<dcscor:item xsi:type="dcsset:SettingsParameterValue">
					<dcscor:parameter>ГоризонтальноеПоложение</dcscor:parameter>
					<dcscor:value xsi:type="v8ui:HorizontalAlign">Center</dcscor:value>
				</dcscor:item>
				<dcscor:item xsi:type="dcsset:SettingsParameterValue">
					<dcscor:parameter>Формат</dcscor:parameter>
					<dcscor:value xsi:type="v8:LocalStringType">
						<v8:item>
							<v8:lang>ru</v8:lang>
							<v8:content>ДФ=yyyy</v8:content>
						</v8:item>
					</dcscor:value>
				</dcscor:item>
			</appearance>
		</field>
		<field xsi:type="DataSetFieldField">
			<dataPath>ПериодМесяц</dataPath>
			<field>ПериодМесяц</field>
			<role>
				<dcscom:periodNumber>3</dcscom:periodNumber>
				<dcscom:periodType>Additional</dcscom:periodType>
			</role>
			<appearance>
				<dcscor:item xsi:type="dcsset:SettingsParameterValue">
					<dcscor:parameter>ГоризонтальноеПоложение</dcscor:parameter>
					<dcscor:value xsi:type="v8ui:HorizontalAlign">Center</dcscor:value>
				</dcscor:item>
				<dcscor:item xsi:type="dcsset:SettingsParameterValue">
					<dcscor:parameter>Формат</dcscor:parameter>
					<dcscor:value xsi:type="v8:LocalStringType">
						<v8:item>
							<v8:lang>ru</v8:lang>
							<v8:content>ДФ=MMMM</v8:content>
						</v8:item>
					</dcscor:value>
				</dcscor:item>
			</appearance>
		</field>
		<field xsi:type="DataSetFieldField">
			<dataPath>СуммаПлан</dataPath>
			<field>СуммаПлан</field>
			<title xsi:type="v8:LocalStringType">
				<v8:item>
					<v8:lang>ru</v8:lang>
					<v8:content>Сумма план</v8:content>
				</v8:item>
			</title>
			<appearance>
				<dcscor:item xsi:type="dcsset:SettingsParameterValue">
					<dcscor:parameter>Формат</dcscor:parameter>
					<dcscor:value xsi:type="v8:LocalStringType">
						<v8:item>
							<v8:lang>ru</v8:lang>
							<v8:content>ЧДЦ=2</v8:content>
						</v8:item>
					</dcscor:value>
				</dcscor:item>
			</appearance>
		</field>
		<item xsi:type="DataSetQuery">
			<name>ПланЖЦП</name>
			<field xsi:type="DataSetFieldField">
				<dataPath>Ресурс.ЕдиницаИзмерения</dataPath>
				<field>ЕдиницаИзмерения</field>
			</field>
			<field xsi:type="DataSetFieldField">
				<dataPath>Ресурс</dataPath>
				<field>Ресурс</field>
			</field>
			<field xsi:type="DataSetFieldField">
				<dataPath>КлючСтроки</dataPath>
				<field>КлючСтроки</field>
			</field>
			<field xsi:type="DataSetFieldField">
				<dataPath>Период</dataPath>
				<field>Период</field>
				<title xsi:type="v8:LocalStringType">
					<v8:item>
						<v8:lang>ru</v8:lang>
						<v8:content>Период</v8:content>
					</v8:item>
				</title>
			</field>
			<field xsi:type="DataSetFieldField">
				<dataPath>КоличествоПлан</dataPath>
				<field>КоличествоПлан</field>
				<title xsi:type="v8:LocalStringType">
					<v8:item>
						<v8:lang>ru</v8:lang>
						<v8:content>Количество план</v8:content>
					</v8:item>
				</title>
			</field>
			<field xsi:type="DataSetFieldField">
				<dataPath>Регистратор</dataPath>
				<field>Регистратор</field>
			</field>
			<field xsi:type="DataSetFieldField">
				<dataPath>ПериодГод</dataPath>
				<field>ПериодГод</field>
				<title xsi:type="v8:LocalStringType">
					<v8:item>
						<v8:lang>ru</v8:lang>
						<v8:content>Период год</v8:content>
					</v8:item>
				</title>
			</field>
			<field xsi:type="DataSetFieldField">
				<dataPath>ПериодМесяц</dataPath>
				<field>ПериодМесяц</field>
				<title xsi:type="v8:LocalStringType">
					<v8:item>
						<v8:lang>ru</v8:lang>
						<v8:content>Период месяц</v8:content>
					</v8:item>
				</title>
			</field>
			<field xsi:type="DataSetFieldField">
				<dataPath>СуммаПлан</dataPath>
				<field>СуммаПлан</field>
				<title xsi:type="v8:LocalStringType">
					<v8:item>
						<v8:lang>ru</v8:lang>
						<v8:content>Сумма план</v8:content>
					</v8:item>
				</title>
			</field>
			<dataSource>ИсточникДанных1</dataSource>
			<query>ВЫБРАТЬ
	РСРесурсы.КлючСтроки,
	РСРесурсы.Ресурс,
	ВЫБОР
		КОГДА СУММА(РСРесурсы.Количество) &lt;&gt; 0
			ТОГДА СУММА(РСРесурсы.Сумма) / СУММА(РСРесурсы.Количество)
		ИНАЧЕ 0
	КОНЕЦ КАК ЦенаРесурса
ПОМЕСТИТЬ ВТ_ЦеныРесурсов
ИЗ
	РегистрСведений.ИНАГРО_УГПРРесурсыТрудовые КАК РСРесурсы
ГДЕ
	РСРесурсы.Проект = &amp;Проект
	И РСРесурсы.Версия.ВидВерсии = &amp;ВидВерсииРабочая

СГРУППИРОВАТЬ ПО
	РСРесурсы.КлючСтроки,
	РСРесурсы.Ресурс
;

////////////////////////////////////////////////////////////////////////////////
ВЫБРАТЬ
	"ЖЦП" КАК Период,
	НАЧАЛОПЕРИОДА(РСПотребности.ДатаПлана, ГОД) КАК ПериодГод,
	НАЧАЛОПЕРИОДА(РСПотребности.ДатаПлана, МЕСЯЦ) КАК ПериодМесяц,
	РСПотребности.Ресурс КАК Ресурс,
	РСПотребности.КлючСтроки КАК КлючСтроки,
	РСПотребности.Ресурс.ЕдиницаИзмерения КАК ЕдиницаИзмерения,
	РСПотребности.КоличествоРесурса КАК КоличествоПлан,
	РСПотребности.Регистратор КАК Регистратор,
	ЕСТЬNULL(ВТ_ЦеныРесурсов.ЦенаРесурса, 0) * РСПотребности.КоличествоРесурса КАК СуммаПлан
{ВЫБРАТЬ
	Период,
	КлючСтроки,
	Ресурс.*,
	ЕдиницаИзмерения.*,
	КоличествоПлан,
	Регистратор.*,
	ПериодГод,
	ПериодМесяц,
	СуммаПлан}
ИЗ
	РегистрСведений.ИНАГРО_ПланПотребностейВТрудовыхРесурсах.СрезПоследних(, Проект = &amp;Проект) КАК РСПотребности
		ЛЕВОЕ СОЕДИНЕНИЕ ВТ_ЦеныРесурсов КАК ВТ_ЦеныРесурсов
		ПО РСПотребности.КлючСтроки = ВТ_ЦеныРесурсов.КлючСтроки
			И РСПотребности.Ресурс = ВТ_ЦеныРесурсов.Ресурс
{ГДЕ
	РСПотребности.Ресурс.*,
	РСПотребности.КлючСтроки,
	(НАЧАЛОПЕРИОДА(РСПотребности.ДатаПлана, МЕСЯЦ)) КАК ПериодМесяц}</query>
			<autoFillFields>false</autoFillFields>
		</item>
		<item xsi:type="DataSetQuery">
			<name>ФактЖЦП</name>
			<field xsi:type="DataSetFieldField">
				<dataPath>Ресурс.ЕдиницаИзмерения</dataPath>
				<field>ЕдиницаИзмерения</field>
				<title xsi:type="v8:LocalStringType">
					<v8:item>
						<v8:lang>ru</v8:lang>
						<v8:content>Ресурс.Единица измерения</v8:content>
					</v8:item>
				</title>
			</field>
			<field xsi:type="DataSetFieldField">
				<dataPath>Период</dataPath>
				<field>Период</field>
				<title xsi:type="v8:LocalStringType">
					<v8:item>
						<v8:lang>ru</v8:lang>
						<v8:content>Период</v8:content>
					</v8:item>
				</title>
			</field>
			<field xsi:type="DataSetFieldField">
				<dataPath>Ресурс</dataPath>
				<field>Ресурс</field>
				<role>
					<dcscom:dimension>true</dcscom:dimension>
				</role>
			</field>
			<field xsi:type="DataSetFieldField">
				<dataPath>КоличествоФакт</dataPath>
				<field>КоличествоФакт</field>
				<title xsi:type="v8:LocalStringType">
					<v8:item>
						<v8:lang>ru</v8:lang>
						<v8:content>Количество факт</v8:content>
					</v8:item>
				</title>
			</field>
			<field xsi:type="DataSetFieldField">
				<dataPath>СуммаФакт</dataPath>
				<field>СуммаФакт</field>
				<title xsi:type="v8:LocalStringType">
					<v8:item>
						<v8:lang>ru</v8:lang>
						<v8:content>Сумма факт</v8:content>
					</v8:item>
				</title>
			</field>
			<field xsi:type="DataSetFieldField">
				<dataPath>КлючСтроки</dataPath>
				<field>КлючСтроки</field>
				<role>
					<dcscom:dimension>true</dcscom:dimension>
				</role>
			</field>
			<field xsi:type="DataSetFieldField">
				<dataPath>Регистратор</dataPath>
				<field>Регистратор</field>
				<role>
					<dcscom:periodNumber>1</dcscom:periodNumber>
					<dcscom:periodType>Main</dcscom:periodType>
				</role>
			</field>
			<field xsi:type="DataSetFieldField">
				<dataPath>ПериодГод</dataPath>
				<field>ПериодГод</field>
				<role>
					<dcscom:periodNumber>3</dcscom:periodNumber>
					<dcscom:periodType>Additional</dcscom:periodType>
				</role>
			</field>
			<field xsi:type="DataSetFieldField">
				<dataPath>ПериодМесяц</dataPath>
				<field>ПериодМесяц</field>
				<role>
					<dcscom:periodNumber>2</dcscom:periodNumber>
					<dcscom:periodType>Additional</dcscom:periodType>
				</role>
			</field>
			<dataSource>ИсточникДанных1</dataSource>
			<query>ВЫБРАТЬ
	"ЖЦП" КАК Период,
	РНРасходРесурсов.ПериодГод КАК ПериодГод,
	РНРасходРесурсов.ПериодМесяц КАК ПериодМесяц,
	РНРасходРесурсов.Ресурс КАК Ресурс,
	РНРасходРесурсов.КлючСтроки КАК КлючСтроки,
	РНРасходРесурсов.Ресурс.ЕдиницаИзмерения КАК ЕдиницаИзмерения,
	РНРасходРесурсов.КоличествоРесурсаОборот КАК КоличествоФакт,
	РНРасходРесурсов.СуммаОборот КАК СуммаФакт,
	РНРасходРесурсов.Регистратор КАК Регистратор
{ВЫБРАТЬ
	Период,
	ПериодГод,
	ПериодМесяц,
	Регистратор.*,
	Ресурс.*,
	КлючСтроки,
	ЕдиницаИзмерения.*,
	КоличествоФакт,
	СуммаФакт}
ИЗ
	РегистрНакопления.ИНАГРО_УчетРаботыТрудовыхРесурсов.Обороты(, , Авто, Проект = &amp;Проект) КАК РНРасходРесурсов
{ГДЕ
	РНРасходРесурсов.Ресурс.*,
	РНРасходРесурсов.КлючСтроки,
	РНРасходРесурсов.ПериодМесяц}</query>
			<autoFillFields>false</autoFillFields>
		</item>
	</dataSet>
	<dataSet xsi:type="DataSetQuery">
		<name>ПредставлениеРабот</name>
		<field xsi:type="DataSetFieldField">
			<dataPath>ВидРаботы</dataPath>
			<field>ВидРаботы</field>
			<useRestriction>
				<order>true</order>
			</useRestriction>
			<attributeUseRestriction>
				<order>true</order>
			</attributeUseRestriction>
			<inputParameters>
				<dcscor:item>
					<dcscor:parameter>СвязиПараметровВыбора</dcscor:parameter>
					<dcscor:value xsi:type="dcscor:ChoiceParameterLinks">
						<dcscor:item>
							<dcscor:choiceParameter>Отбор.Владелец</dcscor:choiceParameter>
							<dcscor:value>ПараметрыДанных.Проект</dcscor:value>
							<dcscor:mode xmlns:d8p1="http://v8.1c.ru/8.1/data/enterprise" xsi:type="d8p1:LinkedValueChangeMode">Clear</dcscor:mode>
						</dcscor:item>
					</dcscor:value>
				</dcscor:item>
			</inputParameters>
		</field>
		<field xsi:type="DataSetFieldField">
			<dataPath>ВидРаботы.КодWBS</dataPath>
			<field>КодWBS</field>
			<useRestriction>
				<field>true</field>
				<group>true</group>
				<order>true</order>
			</useRestriction>
		</field>
		<field xsi:type="DataSetFieldField">
			<dataPath>КлючСтроки</dataPath>
			<field>КлючСтроки</field>
			<title xsi:type="v8:LocalStringType">
				<v8:item>
					<v8:lang>ru</v8:lang>
					<v8:content>Код WBS</v8:content>
				</v8:item>
			</title>
			<useRestriction>
				<field>true</field>
				<group>true</group>
				<order>true</order>
			</useRestriction>
			<role>
				<dcscom:dimension>true</dcscom:dimension>
			</role>
			<presentationExpression>ВидРаботы.КодWBS</presentationExpression>
			<orderExpression>
				<dcscom:expression>ВидРаботы.КодWBS</dcscom:expression>
				<dcscom:orderType>Asc</dcscom:orderType>
				<dcscom:autoOrder>false</dcscom:autoOrder>
			</orderExpression>
		</field>
		<field xsi:type="DataSetFieldField">
			<dataPath>ВидРаботы.НомерВСтруктуре</dataPath>
			<field>НомерВСтруктуре</field>
		</field>
		<dataSource>ИсточникДанных1</dataSource>
		<query>ВЫБРАТЬ РАЗЛИЧНЫЕ
	ИНАГРО_УГПРРаботы.КлючСтроки КАК КлючСтроки,
	МАКСИМУМ(ИНАГРО_УГПРРаботы.КодWBS) КАК КодWBS,
	МАКСИМУМ(ИНАГРО_УГПРРаботы.ВидРаботы) КАК ВидРаботы,
	МАКСИМУМ(ИНАГРО_УГПРРаботы.НомерВСтруктуре) КАК НомерВСтруктуре
{ВЫБРАТЬ
	КлючСтроки,
	КодWBS,
	ВидРаботы.*,
	НомерВСтруктуре}
ИЗ
	РегистрСведений.ИНАГРО_УГПРРаботы КАК ИНАГРО_УГПРРаботы
ГДЕ
	ИНАГРО_УГПРРаботы.Проект = &amp;Проект
	И ИНАГРО_УГПРРаботы.Версия.ВидВерсии = &amp;ВидВерсииРабочая
{ГДЕ
	ИНАГРО_УГПРРаботы.ВидРаботы.*}

СГРУППИРОВАТЬ ПО
	ИНАГРО_УГПРРаботы.КлючСтроки</query>
		<autoFillFields>false</autoFillFields>
	</dataSet>
	<dataSet xsi:type="DataSetQuery">
		<name>ТаблицаИерархии</name>
		<field xsi:type="DataSetFieldField">
			<dataPath>КлючСтроки</dataPath>
			<field>КлючСтроки</field>
			<title xsi:type="v8:LocalStringType">
				<v8:item>
					<v8:lang>ru</v8:lang>
					<v8:content>Ключ строки</v8:content>
				</v8:item>
			</title>
			<useRestriction>
				<field>true</field>
				<group>true</group>
			</useRestriction>
			<presentationExpression>КлючСтроки.КодWBS</presentationExpression>
			<orderExpression>
				<dcscom:expression>КлючСтроки.КодWBS</dcscom:expression>
				<dcscom:orderType>Asc</dcscom:orderType>
				<dcscom:autoOrder>false</dcscom:autoOrder>
			</orderExpression>
			<orderExpression>
				<dcscom:expression>КлючСтроки.НомерВСтруктуре</dcscom:expression>
				<dcscom:orderType>Asc</dcscom:orderType>
				<dcscom:autoOrder>false</dcscom:autoOrder>
			</orderExpression>
		</field>
		<field xsi:type="DataSetFieldField">
			<dataPath>КлючСвязи</dataPath>
			<field>КлючСвязи</field>
			<useRestriction>
				<field>true</field>
				<group>true</group>
				<order>true</order>
			</useRestriction>
		</field>
		<field xsi:type="DataSetFieldField">
			<dataPath>Версия</dataPath>
			<field>Версия</field>
			<title xsi:type="v8:LocalStringType">
				<v8:item>
					<v8:lang>ru</v8:lang>
					<v8:content>Версия</v8:content>
				</v8:item>
			</title>
			<useRestriction>
				<field>true</field>
				<group>true</group>
				<order>true</order>
			</useRestriction>
			<attributeUseRestriction>
				<field>true</field>
				<group>true</group>
				<order>true</order>
			</attributeUseRestriction>
		</field>
		<field xsi:type="DataSetFieldField">
			<dataPath>ВидРаботы</dataPath>
			<field>ВидРаботы</field>
			<title xsi:type="v8:LocalStringType">
				<v8:item>
					<v8:lang>ru</v8:lang>
					<v8:content>Вид работы</v8:content>
				</v8:item>
			</title>
			<useRestriction>
				<field>true</field>
				<group>true</group>
				<order>true</order>
			</useRestriction>
			<attributeUseRestriction>
				<field>true</field>
				<group>true</group>
				<order>true</order>
			</attributeUseRestriction>
		</field>
		<field xsi:type="DataSetFieldField">
			<dataPath>КлючСтроки.КодWBS</dataPath>
			<field>КодWBS</field>
			<useRestriction>
				<field>true</field>
				<group>true</group>
				<order>true</order>
			</useRestriction>
		</field>
		<field xsi:type="DataSetFieldField">
			<dataPath>КлючСтроки.НомерВСтруктуре</dataPath>
			<field>НомерВСтруктуре</field>
			<title xsi:type="v8:LocalStringType">
				<v8:item>
					<v8:lang>ru</v8:lang>
					<v8:content>Номер в структуре</v8:content>
				</v8:item>
			</title>
			<useRestriction>
				<field>true</field>
				<group>true</group>
				<order>true</order>
			</useRestriction>
		</field>
		<dataSource>ИсточникДанных1</dataSource>
		<query>ВЫБРАТЬ
	ИНАГРО_УГПРРаботы.Версия КАК Версия,
	ИНАГРО_УГПРРаботы.КлючСтроки КАК КлючСтроки,
	ИНАГРО_УГПРРаботы.КлючСвязи КАК КлючСвязи,
	ИНАГРО_УГПРРаботы.ВидРаботы КАК ВидРаботы,
	МИНИМУМ(ИНАГРО_УГПРРаботы.КодWBS) КАК КодWBS,
	МИНИМУМ(ИНАГРО_УГПРРаботы.НомерВСтруктуре) КАК НомерВСтруктуре
{ВЫБРАТЬ
	Версия.*,
	КлючСтроки,
	КлючСвязи,
	ВидРаботы.*,
	КодWBS,
	НомерВСтруктуре}
ИЗ
	РегистрСведений.ИНАГРО_УГПРРаботы КАК ИНАГРО_УГПРРаботы
ГДЕ
	ИНАГРО_УГПРРаботы.Проект = &amp;Проект
	И ИНАГРО_УГПРРаботы.Версия.ВидВерсии = &amp;ВидВерсииРабочая

СГРУППИРОВАТЬ ПО
	ИНАГРО_УГПРРаботы.КлючСтроки,
	ИНАГРО_УГПРРаботы.Версия,
	ИНАГРО_УГПРРаботы.КлючСвязи,
	ИНАГРО_УГПРРаботы.ВидРаботы</query>
		<autoFillFields>false</autoFillFields>
	</dataSet>
	<dataSetLink>
		<sourceDataSet>ДанныеРесурсы</sourceDataSet>
		<destinationDataSet>ПредставлениеРабот</destinationDataSet>
		<sourceExpression>КлючСтроки</sourceExpression>
		<destinationExpression>КлючСтроки</destinationExpression>
		<required>false</required>
	</dataSetLink>
	<dataSetLink>
		<sourceDataSet>ТаблицаИерархии</sourceDataSet>
		<destinationDataSet>ТаблицаИерархии</destinationDataSet>
		<sourceExpression>КлючСвязи</sourceExpression>
		<destinationExpression>КлючСтроки</destinationExpression>
	</dataSetLink>
	<dataSetLink>
		<sourceDataSet>ДанныеРесурсы</sourceDataSet>
		<destinationDataSet>ТаблицаИерархии</destinationDataSet>
		<sourceExpression>КлючСтроки</sourceExpression>
		<destinationExpression>КлючСтроки</destinationExpression>
	</dataSetLink>
	<calculatedField>
		<dataPath>КоличествоОтклонение</dataPath>
		<expression>isnull(КоличествоПлан,0) - isnull(КоличествоФакт,0)</expression>
		<title xsi:type="v8:LocalStringType">
			<v8:item>
				<v8:lang>ru</v8:lang>
				<v8:content>Количество отклонение</v8:content>
			</v8:item>
		</title>
		<appearance>
			<dcscor:item xsi:type="dcsset:SettingsParameterValue">
				<dcscor:parameter>Формат</dcscor:parameter>
				<dcscor:value xsi:type="v8:LocalStringType">
					<v8:item>
						<v8:lang>ru</v8:lang>
						<v8:content>ЧДЦ=4</v8:content>
					</v8:item>
				</dcscor:value>
			</dcscor:item>
			<dcscor:item xsi:type="dcsset:SettingsParameterValue">
				<dcscor:parameter>ВыделятьОтрицательные</dcscor:parameter>
				<dcscor:value xsi:type="xs:boolean">true</dcscor:value>
			</dcscor:item>
		</appearance>
	</calculatedField>
	<calculatedField>
		<dataPath>СуммаОтклонение</dataPath>
		<expression>isnull(СуммаПлан,0) - isnull(СуммаФакт,0)</expression>
		<title xsi:type="v8:LocalStringType">
			<v8:item>
				<v8:lang>ru</v8:lang>
				<v8:content>Сумма отклонение</v8:content>
			</v8:item>
		</title>
		<appearance>
			<dcscor:item xsi:type="dcsset:SettingsParameterValue">
				<dcscor:parameter>Формат</dcscor:parameter>
				<dcscor:value xsi:type="v8:LocalStringType">
					<v8:item>
						<v8:lang>ru</v8:lang>
						<v8:content>ЧДЦ=2</v8:content>
					</v8:item>
				</dcscor:value>
			</dcscor:item>
			<dcscor:item xsi:type="dcsset:SettingsParameterValue">
				<dcscor:parameter>ВыделятьОтрицательные</dcscor:parameter>
				<dcscor:value xsi:type="xs:boolean">true</dcscor:value>
			</dcscor:item>
		</appearance>
	</calculatedField>
	<calculatedField>
		<dataPath>ЦенаПлан</dataPath>
		<expression>выбор когда  isnull(КоличествоПлан,0) &lt;&gt; 0 тогда isnull(СуммаПлан,0) / isnull(КоличествоПлан,0) иначе 0 конец</expression>
		<title xsi:type="v8:LocalStringType">
			<v8:item>
				<v8:lang>ru</v8:lang>
				<v8:content>Цена план</v8:content>
			</v8:item>
		</title>
		<appearance>
			<dcscor:item xsi:type="dcsset:SettingsParameterValue">
				<dcscor:parameter>Формат</dcscor:parameter>
				<dcscor:value xsi:type="v8:LocalStringType">
					<v8:item>
						<v8:lang>ru</v8:lang>
						<v8:content>ЧДЦ=2</v8:content>
					</v8:item>
				</dcscor:value>
			</dcscor:item>
		</appearance>
	</calculatedField>
	<calculatedField>
		<dataPath>ЦенаФакт</dataPath>
		<expression>выбор когда  isnull(КоличествоФакт,0) &lt;&gt; 0 тогда isnull(СуммаФакт,0) / isnull(КоличествоФакт,0) иначе 0 конец</expression>
		<title xsi:type="v8:LocalStringType">
			<v8:item>
				<v8:lang>ru</v8:lang>
				<v8:content>Цена факт</v8:content>
			</v8:item>
		</title>
		<appearance>
			<dcscor:item xsi:type="dcsset:SettingsParameterValue">
				<dcscor:parameter>Формат</dcscor:parameter>
				<dcscor:value xsi:type="v8:LocalStringType">
					<v8:item>
						<v8:lang>ru</v8:lang>
						<v8:content>ЧДЦ=2</v8:content>
					</v8:item>
				</dcscor:value>
			</dcscor:item>
		</appearance>
	</calculatedField>
	<totalField>
		<dataPath>КоличествоПлан</dataPath>
		<expression>Сумма(КоличествоПлан)</expression>
		<group>Ресурс</group>
	</totalField>
	<totalField>
		<dataPath>СуммаФакт</dataPath>
		<expression>Сумма(СуммаФакт)</expression>
	</totalField>
	<totalField>
		<dataPath>КоличествоФакт</dataPath>
		<expression>Сумма(КоличествоФакт)</expression>
		<group>Ресурс</group>
	</totalField>
	<totalField>
		<dataPath>КоличествоОтклонение</dataPath>
		<expression>Сумма(КоличествоОтклонение)</expression>
		<group>Ресурс</group>
	</totalField>
	<totalField>
		<dataPath>СуммаОтклонение</dataPath>
		<expression>Сумма(СуммаОтклонение)</expression>
	</totalField>
	<totalField>
		<dataPath>СуммаПлан</dataPath>
		<expression>Сумма(СуммаПлан)</expression>
	</totalField>
	<totalField>
		<dataPath>ЦенаПлан</dataPath>
		<expression>Максимум(ЦенаПлан)</expression>
		<group>Ресурс</group>
	</totalField>
	<totalField>
		<dataPath>ЦенаФакт</dataPath>
		<expression>Максимум(ЦенаФакт)</expression>
		<group>Ресурс</group>
	</totalField>
	<parameter>
		<name>СтандартныйПериод</name>
		<title xsi:type="v8:LocalStringType">
			<v8:item>
				<v8:lang>ru</v8:lang>
				<v8:content>Период отчета</v8:content>
			</v8:item>
		</title>
		<valueType>
			<v8:Type>v8:StandardPeriod</v8:Type>
		</valueType>
		<value xsi:type="v8:StandardPeriod">
			<v8:variant xsi:type="v8:StandardPeriodVariant">Custom</v8:variant>
			<v8:startDate>0001-01-01T00:00:00</v8:startDate>
			<v8:endDate>0001-01-01T00:00:00</v8:endDate>
		</value>
		<useRestriction>false</useRestriction>
		<use>Always</use>
	</parameter>
	<parameter>
		<name>Проект</name>
		<title xsi:type="v8:LocalStringType">
			<v8:item>
				<v8:lang>ru</v8:lang>
				<v8:content>Проект</v8:content>
			</v8:item>
		</title>
		<value xsi:nil="true"/>
		<useRestriction>false</useRestriction>
		<denyIncompleteValues>true</denyIncompleteValues>
		<use>Always</use>
	</parameter>
	<parameter>
		<name>ВидВерсииРабочая</name>
		<title xsi:type="v8:LocalStringType">
			<v8:item>
				<v8:lang>ru</v8:lang>
				<v8:content>Вид версии рабочая</v8:content>
			</v8:item>
		</title>
		<value xsi:type="dcscor:DesignTimeValue">Перечисление.ИНАГРО_ВидВерсии.Рабочая</value>
		<useRestriction>true</useRestriction>
	</parameter>
	<settingsVariant>
		<dcsset:name>ПланФактТрудовые</dcsset:name>
		<dcsset:presentation xsi:type="v8:LocalStringType">
			<v8:item>
				<v8:lang>ru</v8:lang>
				<v8:content>План-фактный анализ использования трудовых ресурсов</v8:content>
			</v8:item>
			<v8:item>
				<v8:lang>en</v8:lang>
				<v8:content>Основной</v8:content>
			</v8:item>
		</dcsset:presentation>
		<dcsset:settings xmlns:style="http://v8.1c.ru/8.1/data/ui/style" xmlns:sys="http://v8.1c.ru/8.1/data/ui/fonts/system" xmlns:web="http://v8.1c.ru/8.1/data/ui/colors/web" xmlns:win="http://v8.1c.ru/8.1/data/ui/colors/windows">
			<dcsset:selection>
				<dcsset:item xsi:type="dcsset:SelectedItemAuto"/>
			</dcsset:selection>
			<dcsset:filter>
				<dcsset:item xsi:type="dcsset:FilterItemComparison">
					<dcsset:use>false</dcsset:use>
					<dcsset:left xsi:type="dcscor:Field">Ресурс</dcsset:left>
					<dcsset:comparisonType>Equal</dcsset:comparisonType>
					<dcsset:right xsi:type="dcscor:DesignTimeValue">Справочник.СМ_Ресурсы.ПустаяСсылка</dcsset:right>
					<dcsset:userSettingID>31d41ffa-a303-43bb-82c4-b9f55df4e3e2</dcsset:userSettingID>
				</dcsset:item>
				<dcsset:item xsi:type="dcsset:FilterItemComparison">
					<dcsset:use>false</dcsset:use>
					<dcsset:left xsi:type="dcscor:Field">ВидРаботы</dcsset:left>
					<dcsset:comparisonType>Equal</dcsset:comparisonType>
					<dcsset:right xsi:type="dcscor:DesignTimeValue">Справочник.ИНАГРО_ВидыРаботПроект.ПустаяСсылка</dcsset:right>
					<dcsset:userSettingID>30b4a8bf-967e-4dfb-bf76-c75e67b410d7</dcsset:userSettingID>
				</dcsset:item>
			</dcsset:filter>
			<dcsset:dataParameters>
				<dcscor:item xsi:type="dcsset:SettingsParameterValue">
					<dcscor:parameter>СтандартныйПериод</dcscor:parameter>
					<dcscor:value xsi:type="v8:StandardPeriod">
						<v8:variant xsi:type="v8:StandardPeriodVariant">ThisYear</v8:variant>
					</dcscor:value>
					<dcsset:userSettingID>f3f9ec21-5764-4f1e-a7e9-915260030b53</dcsset:userSettingID>
				</dcscor:item>
				<dcscor:item xsi:type="dcsset:SettingsParameterValue">
					<dcscor:parameter>Проект</dcscor:parameter>
					<dcscor:value xsi:type="dcscor:DesignTimeValue">Справочник.Проекты.ПустаяСсылка</dcscor:value>
					<dcsset:userSettingID>4bff7f1d-d833-4c97-93a5-14c17cc79a0d</dcsset:userSettingID>
				</dcscor:item>
				<dcscor:item xsi:type="dcsset:SettingsParameterValue">
					<dcscor:use>false</dcscor:use>
					<dcscor:parameter>ВидВерсииРабочая</dcscor:parameter>
					<dcscor:value xsi:nil="true"/>
				</dcscor:item>
			</dcsset:dataParameters>
			<dcsset:outputParameters>
				<dcscor:item xsi:type="dcsset:SettingsParameterValue">
					<dcscor:parameter>МакетОформления</dcscor:parameter>
					<dcscor:value xsi:type="xs:string">Море</dcscor:value>
				</dcscor:item>
				<dcscor:item xsi:type="dcsset:SettingsParameterValue">
					<dcscor:parameter>Заголовок</dcscor:parameter>
					<dcscor:value xsi:type="v8:LocalStringType">
						<v8:item>
							<v8:lang>ru</v8:lang>
							<v8:content>План-фактный анализ использования трудовых ресурсов</v8:content>
						</v8:item>
					</dcscor:value>
				</dcscor:item>
			</dcsset:outputParameters>
			<dcsset:item xsi:type="dcsset:StructureItemTable">
				<dcsset:column>
					<dcsset:name>Общий план</dcsset:name>
					<dcsset:groupItems>
						<dcsset:item xsi:type="dcsset:GroupItemField">
							<dcsset:field>Период</dcsset:field>
							<dcsset:groupType>Items</dcsset:groupType>
							<dcsset:periodAdditionType>None</dcsset:periodAdditionType>
							<dcsset:periodAdditionBegin xsi:type="xs:dateTime">0001-01-01T00:00:00</dcsset:periodAdditionBegin>
							<dcsset:periodAdditionEnd xsi:type="xs:dateTime">0001-01-01T00:00:00</dcsset:periodAdditionEnd>
						</dcsset:item>
					</dcsset:groupItems>
					<dcsset:order>
						<dcsset:item xsi:type="dcsset:OrderItemAuto"/>
					</dcsset:order>
					<dcsset:selection>
						<dcsset:item xsi:type="dcsset:SelectedItemField">
							<dcsset:field>Период</dcsset:field>
						</dcsset:item>
						<dcsset:item xsi:type="dcsset:SelectedItemFolder">
							<dcsset:lwsTitle>
								<v8:item>
									<v8:lang>ru</v8:lang>
									<v8:content>Общий план</v8:content>
								</v8:item>
							</dcsset:lwsTitle>
							<dcsset:item xsi:type="dcsset:SelectedItemField">
								<dcsset:field>КоличествоПлан</dcsset:field>
								<dcsset:lwsTitle>
									<v8:item>
										<v8:lang>ru</v8:lang>
										<v8:content>Количество</v8:content>
									</v8:item>
								</dcsset:lwsTitle>
							</dcsset:item>
							<dcsset:placement>Auto</dcsset:placement>
						</dcsset:item>
					</dcsset:selection>
					<dcsset:outputParameters>
						<dcscor:item xsi:type="dcsset:SettingsParameterValue">
							<dcscor:use>false</dcscor:use>
							<dcscor:parameter>РасположениеИтогов</dcscor:parameter>
							<dcscor:value xsi:type="dcscor:DataCompositionTotalPlacement">None</dcscor:value>
						</dcscor:item>
						<dcscor:item xsi:type="dcsset:SettingsParameterValue">
							<dcscor:parameter>РасположениеОбщихИтогов</dcscor:parameter>
							<dcscor:value xsi:type="dcscor:DataCompositionTotalPlacement">None</dcscor:value>
						</dcscor:item>
					</dcsset:outputParameters>
				</dcsset:column>
				<dcsset:column>
					<dcsset:name>Накопительно</dcsset:name>
					<dcsset:groupItems>
						<dcsset:item xsi:type="dcsset:GroupItemField">
							<dcsset:field>Период</dcsset:field>
							<dcsset:groupType>Items</dcsset:groupType>
							<dcsset:periodAdditionType>None</dcsset:periodAdditionType>
							<dcsset:periodAdditionBegin xsi:type="xs:dateTime">0001-01-01T00:00:00</dcsset:periodAdditionBegin>
							<dcsset:periodAdditionEnd xsi:type="xs:dateTime">0001-01-01T00:00:00</dcsset:periodAdditionEnd>
						</dcsset:item>
					</dcsset:groupItems>
					<dcsset:filter>
						<dcsset:item xsi:type="dcsset:FilterItemComparison">
							<dcsset:use>false</dcsset:use>
							<dcsset:left xsi:type="dcscor:Field">ПериодМесяц</dcsset:left>
							<dcsset:comparisonType>LessOrEqual</dcsset:comparisonType>
							<dcsset:right xsi:type="v8:StandardBeginningDate">
								<v8:variant xsi:type="v8:StandardBeginningDateVariant">Custom</v8:variant>
								<v8:date>0001-01-01T00:00:00</v8:date>
							</dcsset:right>
							<dcsset:viewMode>Inaccessible</dcsset:viewMode>
							<dcsset:userSettingID>085bfe46-65c1-4752-b4fc-ec6dc58c502d</dcsset:userSettingID>
							<dcsset:userSettingPresentation xsi:type="v8:LocalStringType">
								<v8:item>
									<v8:lang>ru</v8:lang>
									<v8:content>КонецПериода</v8:content>
								</v8:item>
							</dcsset:userSettingPresentation>
						</dcsset:item>
					</dcsset:filter>
					<dcsset:order>
						<dcsset:item xsi:type="dcsset:OrderItemAuto"/>
					</dcsset:order>
					<dcsset:selection>
						<dcsset:item xsi:type="dcsset:SelectedItemField">
							<dcsset:field>Период</dcsset:field>
						</dcsset:item>
						<dcsset:item xsi:type="dcsset:SelectedItemFolder">
							<dcsset:lwsTitle>
								<v8:item>
									<v8:lang>ru</v8:lang>
									<v8:content>План с нарастающим</v8:content>
								</v8:item>
							</dcsset:lwsTitle>
							<dcsset:item xsi:type="dcsset:SelectedItemField">
								<dcsset:field>КоличествоПлан</dcsset:field>
								<dcsset:lwsTitle>
									<v8:item>
										<v8:lang>ru</v8:lang>
										<v8:content>Количество</v8:content>
									</v8:item>
								</dcsset:lwsTitle>
							</dcsset:item>
							<dcsset:item xsi:type="dcsset:SelectedItemField">
								<dcsset:use>false</dcsset:use>
								<dcsset:field>ЦенаПлан</dcsset:field>
								<dcsset:lwsTitle>
									<v8:item>
										<v8:lang>ru</v8:lang>
										<v8:content>Цена за ед.</v8:content>
									</v8:item>
								</dcsset:lwsTitle>
							</dcsset:item>
							<dcsset:item xsi:type="dcsset:SelectedItemField">
								<dcsset:field>СуммаПлан</dcsset:field>
								<dcsset:lwsTitle>
									<v8:item>
										<v8:lang>ru</v8:lang>
										<v8:content>Сумма</v8:content>
									</v8:item>
								</dcsset:lwsTitle>
							</dcsset:item>
							<dcsset:placement>Auto</dcsset:placement>
						</dcsset:item>
						<dcsset:item xsi:type="dcsset:SelectedItemFolder">
							<dcsset:lwsTitle>
								<v8:item>
									<v8:lang>ru</v8:lang>
									<v8:content>Факт с нарастающим</v8:content>
								</v8:item>
							</dcsset:lwsTitle>
							<dcsset:item xsi:type="dcsset:SelectedItemField">
								<dcsset:field>КоличествоФакт</dcsset:field>
								<dcsset:lwsTitle>
									<v8:item>
										<v8:lang>ru</v8:lang>
										<v8:content>Количество</v8:content>
									</v8:item>
								</dcsset:lwsTitle>
							</dcsset:item>
							<dcsset:item xsi:type="dcsset:SelectedItemField">
								<dcsset:use>false</dcsset:use>
								<dcsset:field>ЦенаФакт</dcsset:field>
								<dcsset:lwsTitle>
									<v8:item>
										<v8:lang>ru</v8:lang>
										<v8:content>Цена за ед.</v8:content>
									</v8:item>
								</dcsset:lwsTitle>
							</dcsset:item>
							<dcsset:item xsi:type="dcsset:SelectedItemField">
								<dcsset:field>СуммаФакт</dcsset:field>
								<dcsset:lwsTitle>
									<v8:item>
										<v8:lang>ru</v8:lang>
										<v8:content>Сумма</v8:content>
									</v8:item>
								</dcsset:lwsTitle>
							</dcsset:item>
							<dcsset:placement>Auto</dcsset:placement>
						</dcsset:item>
						<dcsset:item xsi:type="dcsset:SelectedItemFolder">
							<dcsset:use>false</dcsset:use>
							<dcsset:lwsTitle>
								<v8:item>
									<v8:lang>ru</v8:lang>
									<v8:content>Остаток потребности</v8:content>
								</v8:item>
							</dcsset:lwsTitle>
							<dcsset:item xsi:type="dcsset:SelectedItemField">
								<dcsset:use>false</dcsset:use>
								<dcsset:field>КоличествоОтклонение</dcsset:field>
								<dcsset:lwsTitle>
									<v8:item>
										<v8:lang>ru</v8:lang>
										<v8:content>Количество</v8:content>
									</v8:item>
								</dcsset:lwsTitle>
							</dcsset:item>
							<dcsset:item xsi:type="dcsset:SelectedItemField">
								<dcsset:use>false</dcsset:use>
								<dcsset:field>СуммаОтклонение</dcsset:field>
								<dcsset:lwsTitle>
									<v8:item>
										<v8:lang>ru</v8:lang>
										<v8:content>Сумма</v8:content>
									</v8:item>
								</dcsset:lwsTitle>
							</dcsset:item>
							<dcsset:placement>Auto</dcsset:placement>
						</dcsset:item>
					</dcsset:selection>
					<dcsset:outputParameters>
						<dcscor:item xsi:type="dcsset:SettingsParameterValue">
							<dcscor:use>false</dcscor:use>
							<dcscor:parameter>РасположениеИтогов</dcscor:parameter>
							<dcscor:value xsi:type="dcscor:DataCompositionTotalPlacement">None</dcscor:value>
						</dcscor:item>
						<dcscor:item xsi:type="dcsset:SettingsParameterValue">
							<dcscor:parameter>РасположениеОбщихИтогов</dcscor:parameter>
							<dcscor:value xsi:type="dcscor:DataCompositionTotalPlacement">None</dcscor:value>
						</dcscor:item>
					</dcsset:outputParameters>
				</dcsset:column>
				<dcsset:column>
					<dcsset:name>Общий план</dcsset:name>
					<dcsset:groupItems>
						<dcsset:item xsi:type="dcsset:GroupItemField">
							<dcsset:field>ПериодГод</dcsset:field>
							<dcsset:groupType>Items</dcsset:groupType>
							<dcsset:periodAdditionType>None</dcsset:periodAdditionType>
							<dcsset:periodAdditionBegin xsi:type="xs:dateTime">0001-01-01T00:00:00</dcsset:periodAdditionBegin>
							<dcsset:periodAdditionEnd xsi:type="xs:dateTime">0001-01-01T00:00:00</dcsset:periodAdditionEnd>
						</dcsset:item>
					</dcsset:groupItems>
					<dcsset:order>
						<dcsset:item xsi:type="dcsset:OrderItemAuto"/>
					</dcsset:order>
					<dcsset:selection>
						<dcsset:item xsi:type="dcsset:SelectedItemField">
							<dcsset:field>ПериодГод</dcsset:field>
						</dcsset:item>
						<dcsset:item xsi:type="dcsset:SelectedItemFolder">
							<dcsset:lwsTitle>
								<v8:item>
									<v8:lang>ru</v8:lang>
									<v8:content>Общий план</v8:content>
								</v8:item>
							</dcsset:lwsTitle>
							<dcsset:item xsi:type="dcsset:SelectedItemField">
								<dcsset:field>КоличествоПлан</dcsset:field>
								<dcsset:lwsTitle>
									<v8:item>
										<v8:lang>ru</v8:lang>
										<v8:content>Количество</v8:content>
									</v8:item>
								</dcsset:lwsTitle>
							</dcsset:item>
							<dcsset:placement>Auto</dcsset:placement>
						</dcsset:item>
					</dcsset:selection>
					<dcsset:outputParameters>
						<dcscor:item xsi:type="dcsset:SettingsParameterValue">
							<dcscor:parameter>РасположениеОбщихИтогов</dcscor:parameter>
							<dcscor:value xsi:type="dcscor:DataCompositionTotalPlacement">None</dcscor:value>
						</dcscor:item>
					</dcsset:outputParameters>
				</dcsset:column>
				<dcsset:column>
					<dcsset:name>Накопительно</dcsset:name>
					<dcsset:groupItems>
						<dcsset:item xsi:type="dcsset:GroupItemField">
							<dcsset:field>ПериодГод</dcsset:field>
							<dcsset:groupType>Items</dcsset:groupType>
							<dcsset:periodAdditionType>None</dcsset:periodAdditionType>
							<dcsset:periodAdditionBegin xsi:type="xs:dateTime">0001-01-01T00:00:00</dcsset:periodAdditionBegin>
							<dcsset:periodAdditionEnd xsi:type="xs:dateTime">0001-01-01T00:00:00</dcsset:periodAdditionEnd>
						</dcsset:item>
					</dcsset:groupItems>
					<dcsset:filter>
						<dcsset:item xsi:type="dcsset:FilterItemComparison">
							<dcsset:use>false</dcsset:use>
							<dcsset:left xsi:type="dcscor:Field">ПериодМесяц</dcsset:left>
							<dcsset:comparisonType>LessOrEqual</dcsset:comparisonType>
							<dcsset:right xsi:type="v8:StandardBeginningDate">
								<v8:variant xsi:type="v8:StandardBeginningDateVariant">Custom</v8:variant>
								<v8:date>0001-01-01T00:00:00</v8:date>
							</dcsset:right>
							<dcsset:viewMode>Inaccessible</dcsset:viewMode>
							<dcsset:userSettingID>38a97e2c-2fd9-4a19-9dd6-c16512ac58f4</dcsset:userSettingID>
							<dcsset:userSettingPresentation xsi:type="v8:LocalStringType">
								<v8:item>
									<v8:lang>ru</v8:lang>
									<v8:content>КонецПериода</v8:content>
								</v8:item>
							</dcsset:userSettingPresentation>
						</dcsset:item>
					</dcsset:filter>
					<dcsset:order>
						<dcsset:item xsi:type="dcsset:OrderItemAuto"/>
					</dcsset:order>
					<dcsset:selection>
						<dcsset:item xsi:type="dcsset:SelectedItemField">
							<dcsset:field>ПериодГод</dcsset:field>
						</dcsset:item>
						<dcsset:item xsi:type="dcsset:SelectedItemFolder">
							<dcsset:lwsTitle>
								<v8:item>
									<v8:lang>ru</v8:lang>
									<v8:content>План с нарастающим</v8:content>
								</v8:item>
							</dcsset:lwsTitle>
							<dcsset:item xsi:type="dcsset:SelectedItemField">
								<dcsset:field>КоличествоПлан</dcsset:field>
								<dcsset:lwsTitle>
									<v8:item>
										<v8:lang>ru</v8:lang>
										<v8:content>Количество</v8:content>
									</v8:item>
								</dcsset:lwsTitle>
							</dcsset:item>
							<dcsset:item xsi:type="dcsset:SelectedItemField">
								<dcsset:use>false</dcsset:use>
								<dcsset:field>ЦенаПлан</dcsset:field>
								<dcsset:lwsTitle>
									<v8:item>
										<v8:lang>ru</v8:lang>
										<v8:content>Цена за ед.</v8:content>
									</v8:item>
								</dcsset:lwsTitle>
							</dcsset:item>
							<dcsset:item xsi:type="dcsset:SelectedItemField">
								<dcsset:field>СуммаПлан</dcsset:field>
								<dcsset:lwsTitle>
									<v8:item>
										<v8:lang>ru</v8:lang>
										<v8:content>Сумма</v8:content>
									</v8:item>
								</dcsset:lwsTitle>
							</dcsset:item>
							<dcsset:placement>Auto</dcsset:placement>
						</dcsset:item>
						<dcsset:item xsi:type="dcsset:SelectedItemFolder">
							<dcsset:lwsTitle>
								<v8:item>
									<v8:lang>ru</v8:lang>
									<v8:content>Факт с нарастающим</v8:content>
								</v8:item>
							</dcsset:lwsTitle>
							<dcsset:item xsi:type="dcsset:SelectedItemField">
								<dcsset:field>КоличествоФакт</dcsset:field>
								<dcsset:lwsTitle>
									<v8:item>
										<v8:lang>ru</v8:lang>
										<v8:content>Количество</v8:content>
									</v8:item>
								</dcsset:lwsTitle>
							</dcsset:item>
							<dcsset:item xsi:type="dcsset:SelectedItemField">
								<dcsset:use>false</dcsset:use>
								<dcsset:field>ЦенаФакт</dcsset:field>
								<dcsset:lwsTitle>
									<v8:item>
										<v8:lang>ru</v8:lang>
										<v8:content>Цена за ед.</v8:content>
									</v8:item>
								</dcsset:lwsTitle>
							</dcsset:item>
							<dcsset:item xsi:type="dcsset:SelectedItemField">
								<dcsset:field>СуммаФакт</dcsset:field>
								<dcsset:lwsTitle>
									<v8:item>
										<v8:lang>ru</v8:lang>
										<v8:content>Сумма</v8:content>
									</v8:item>
								</dcsset:lwsTitle>
							</dcsset:item>
							<dcsset:placement>Auto</dcsset:placement>
						</dcsset:item>
						<dcsset:item xsi:type="dcsset:SelectedItemFolder">
							<dcsset:use>false</dcsset:use>
							<dcsset:lwsTitle>
								<v8:item>
									<v8:lang>ru</v8:lang>
									<v8:content>Остаток потребности</v8:content>
								</v8:item>
							</dcsset:lwsTitle>
							<dcsset:item xsi:type="dcsset:SelectedItemField">
								<dcsset:use>false</dcsset:use>
								<dcsset:field>КоличествоОтклонение</dcsset:field>
								<dcsset:lwsTitle>
									<v8:item>
										<v8:lang>ru</v8:lang>
										<v8:content>Количество</v8:content>
									</v8:item>
								</dcsset:lwsTitle>
							</dcsset:item>
							<dcsset:item xsi:type="dcsset:SelectedItemField">
								<dcsset:use>false</dcsset:use>
								<dcsset:field>СуммаОтклонение</dcsset:field>
								<dcsset:lwsTitle>
									<v8:item>
										<v8:lang>ru</v8:lang>
										<v8:content>Сумма</v8:content>
									</v8:item>
								</dcsset:lwsTitle>
							</dcsset:item>
							<dcsset:placement>Auto</dcsset:placement>
						</dcsset:item>
					</dcsset:selection>
					<dcsset:outputParameters>
						<dcscor:item xsi:type="dcsset:SettingsParameterValue">
							<dcscor:parameter>РасположениеОбщихИтогов</dcscor:parameter>
							<dcscor:value xsi:type="dcscor:DataCompositionTotalPlacement">None</dcscor:value>
						</dcscor:item>
					</dcsset:outputParameters>
				</dcsset:column>
				<dcsset:column>
					<dcsset:groupItems>
						<dcsset:item xsi:type="dcsset:GroupItemField">
							<dcsset:field>ПериодГод</dcsset:field>
							<dcsset:groupType>Items</dcsset:groupType>
							<dcsset:periodAdditionType>None</dcsset:periodAdditionType>
							<dcsset:periodAdditionBegin xsi:type="xs:dateTime">0001-01-01T00:00:00</dcsset:periodAdditionBegin>
							<dcsset:periodAdditionEnd xsi:type="xs:dateTime">0001-01-01T00:00:00</dcsset:periodAdditionEnd>
						</dcsset:item>
						<dcsset:item xsi:type="dcsset:GroupItemField">
							<dcsset:field>ПериодМесяц</dcsset:field>
							<dcsset:groupType>Items</dcsset:groupType>
							<dcsset:periodAdditionType>None</dcsset:periodAdditionType>
							<dcsset:periodAdditionBegin xsi:type="xs:dateTime">0001-01-01T00:00:00</dcsset:periodAdditionBegin>
							<dcsset:periodAdditionEnd xsi:type="xs:dateTime">0001-01-01T00:00:00</dcsset:periodAdditionEnd>
						</dcsset:item>
					</dcsset:groupItems>
					<dcsset:filter>
						<dcsset:item xsi:type="dcsset:FilterItemComparison">
							<dcsset:use>false</dcsset:use>
							<dcsset:left xsi:type="dcscor:Field">ПериодМесяц</dcsset:left>
							<dcsset:comparisonType>GreaterOrEqual</dcsset:comparisonType>
							<dcsset:right xsi:type="v8:StandardBeginningDate">
								<v8:variant xsi:type="v8:StandardBeginningDateVariant">Custom</v8:variant>
								<v8:date>0001-01-01T00:00:00</v8:date>
							</dcsset:right>
							<dcsset:viewMode>Inaccessible</dcsset:viewMode>
							<dcsset:userSettingID>5415f8aa-16d5-46cd-a2ef-d44cbdad3e41</dcsset:userSettingID>
							<dcsset:userSettingPresentation xsi:type="v8:LocalStringType">
								<v8:item>
									<v8:lang>ru</v8:lang>
									<v8:content>НачалоПериода</v8:content>
								</v8:item>
							</dcsset:userSettingPresentation>
						</dcsset:item>
						<dcsset:item xsi:type="dcsset:FilterItemComparison">
							<dcsset:use>false</dcsset:use>
							<dcsset:left xsi:type="dcscor:Field">ПериодМесяц</dcsset:left>
							<dcsset:comparisonType>LessOrEqual</dcsset:comparisonType>
							<dcsset:right xsi:type="v8:StandardBeginningDate">
								<v8:variant xsi:type="v8:StandardBeginningDateVariant">Custom</v8:variant>
								<v8:date>0001-01-01T00:00:00</v8:date>
							</dcsset:right>
							<dcsset:viewMode>Inaccessible</dcsset:viewMode>
							<dcsset:userSettingID>1dfeb94b-92e5-4439-a144-989d12ef2429</dcsset:userSettingID>
							<dcsset:userSettingPresentation xsi:type="v8:LocalStringType">
								<v8:item>
									<v8:lang>ru</v8:lang>
									<v8:content>КонецПериода</v8:content>
								</v8:item>
							</dcsset:userSettingPresentation>
						</dcsset:item>
					</dcsset:filter>
					<dcsset:order>
						<dcsset:item xsi:type="dcsset:OrderItemAuto"/>
					</dcsset:order>
					<dcsset:selection>
						<dcsset:item xsi:type="dcsset:SelectedItemField">
							<dcsset:field>ПериодГод</dcsset:field>
						</dcsset:item>
						<dcsset:item xsi:type="dcsset:SelectedItemField">
							<dcsset:field>ПериодМесяц</dcsset:field>
						</dcsset:item>
						<dcsset:item xsi:type="dcsset:SelectedItemFolder">
							<dcsset:lwsTitle>
								<v8:item>
									<v8:lang>ru</v8:lang>
									<v8:content>План</v8:content>
								</v8:item>
							</dcsset:lwsTitle>
							<dcsset:item xsi:type="dcsset:SelectedItemField">
								<dcsset:field>КоличествоПлан</dcsset:field>
								<dcsset:lwsTitle>
									<v8:item>
										<v8:lang>ru</v8:lang>
										<v8:content>Количество</v8:content>
									</v8:item>
								</dcsset:lwsTitle>
							</dcsset:item>
							<dcsset:item xsi:type="dcsset:SelectedItemField">
								<dcsset:field>ЦенаПлан</dcsset:field>
								<dcsset:lwsTitle>
									<v8:item>
										<v8:lang>ru</v8:lang>
										<v8:content>Цена за ед.</v8:content>
									</v8:item>
								</dcsset:lwsTitle>
							</dcsset:item>
							<dcsset:item xsi:type="dcsset:SelectedItemField">
								<dcsset:field>СуммаПлан</dcsset:field>
								<dcsset:lwsTitle>
									<v8:item>
										<v8:lang>ru</v8:lang>
										<v8:content>Сумма</v8:content>
									</v8:item>
								</dcsset:lwsTitle>
							</dcsset:item>
							<dcsset:placement>Auto</dcsset:placement>
						</dcsset:item>
						<dcsset:item xsi:type="dcsset:SelectedItemFolder">
							<dcsset:lwsTitle>
								<v8:item>
									<v8:lang>ru</v8:lang>
									<v8:content>Факт</v8:content>
								</v8:item>
							</dcsset:lwsTitle>
							<dcsset:item xsi:type="dcsset:SelectedItemField">
								<dcsset:field>КоличествоФакт</dcsset:field>
								<dcsset:lwsTitle>
									<v8:item>
										<v8:lang>ru</v8:lang>
										<v8:content>Количество</v8:content>
									</v8:item>
								</dcsset:lwsTitle>
							</dcsset:item>
							<dcsset:item xsi:type="dcsset:SelectedItemField">
								<dcsset:field>ЦенаФакт</dcsset:field>
								<dcsset:lwsTitle>
									<v8:item>
										<v8:lang>ru</v8:lang>
										<v8:content>Цена за ед.</v8:content>
									</v8:item>
								</dcsset:lwsTitle>
							</dcsset:item>
							<dcsset:item xsi:type="dcsset:SelectedItemField">
								<dcsset:field>СуммаФакт</dcsset:field>
								<dcsset:lwsTitle>
									<v8:item>
										<v8:lang>ru</v8:lang>
										<v8:content>Сумма</v8:content>
									</v8:item>
								</dcsset:lwsTitle>
							</dcsset:item>
							<dcsset:placement>Auto</dcsset:placement>
						</dcsset:item>
						<dcsset:item xsi:type="dcsset:SelectedItemFolder">
							<dcsset:lwsTitle>
								<v8:item>
									<v8:lang>ru</v8:lang>
									<v8:content>Отклонение</v8:content>
								</v8:item>
							</dcsset:lwsTitle>
							<dcsset:item xsi:type="dcsset:SelectedItemField">
								<dcsset:field>КоличествоОтклонение</dcsset:field>
								<dcsset:lwsTitle>
									<v8:item>
										<v8:lang>ru</v8:lang>
										<v8:content>Количество</v8:content>
									</v8:item>
								</dcsset:lwsTitle>
							</dcsset:item>
							<dcsset:item xsi:type="dcsset:SelectedItemField">
								<dcsset:field>СуммаОтклонение</dcsset:field>
								<dcsset:lwsTitle>
									<v8:item>
										<v8:lang>ru</v8:lang>
										<v8:content>Сумма</v8:content>
									</v8:item>
								</dcsset:lwsTitle>
							</dcsset:item>
							<dcsset:placement>Auto</dcsset:placement>
						</dcsset:item>
					</dcsset:selection>
					<dcsset:outputParameters>
						<dcscor:item xsi:type="dcsset:SettingsParameterValue">
							<dcscor:parameter>РасположениеОбщихИтогов</dcscor:parameter>
							<dcscor:value xsi:type="dcscor:DataCompositionTotalPlacement">None</dcscor:value>
						</dcscor:item>
					</dcsset:outputParameters>
				</dcsset:column>
				<dcsset:column>
					<dcsset:filter>
						<dcsset:item xsi:type="dcsset:FilterItemComparison">
							<dcsset:use>false</dcsset:use>
							<dcsset:left xsi:type="dcscor:Field">ПериодМесяц</dcsset:left>
							<dcsset:comparisonType>GreaterOrEqual</dcsset:comparisonType>
							<dcsset:right xsi:type="v8:StandardBeginningDate">
								<v8:variant xsi:type="v8:StandardBeginningDateVariant">Custom</v8:variant>
								<v8:date>0001-01-01T00:00:00</v8:date>
							</dcsset:right>
							<dcsset:viewMode>Inaccessible</dcsset:viewMode>
							<dcsset:userSettingID>9d8da32f-2af8-48c2-bc14-ff90df4572e4</dcsset:userSettingID>
							<dcsset:userSettingPresentation xsi:type="v8:LocalStringType">
								<v8:item>
									<v8:lang>ru</v8:lang>
									<v8:content>НачалоПериода</v8:content>
								</v8:item>
							</dcsset:userSettingPresentation>
						</dcsset:item>
						<dcsset:item xsi:type="dcsset:FilterItemComparison">
							<dcsset:use>false</dcsset:use>
							<dcsset:left xsi:type="dcscor:Field">ПериодМесяц</dcsset:left>
							<dcsset:comparisonType>LessOrEqual</dcsset:comparisonType>
							<dcsset:right xsi:type="v8:StandardBeginningDate">
								<v8:variant xsi:type="v8:StandardBeginningDateVariant">Custom</v8:variant>
								<v8:date>0001-01-01T00:00:00</v8:date>
							</dcsset:right>
							<dcsset:viewMode>Inaccessible</dcsset:viewMode>
							<dcsset:userSettingID>4311d295-5868-4f38-bd85-5fb042972a34</dcsset:userSettingID>
							<dcsset:userSettingPresentation xsi:type="v8:LocalStringType">
								<v8:item>
									<v8:lang>ru</v8:lang>
									<v8:content>КонецПериода</v8:content>
								</v8:item>
							</dcsset:userSettingPresentation>
						</dcsset:item>
					</dcsset:filter>
					<dcsset:order>
						<dcsset:item xsi:type="dcsset:OrderItemAuto"/>
					</dcsset:order>
					<dcsset:selection>
						<dcsset:item xsi:type="dcsset:SelectedItemFolder">
							<dcsset:lwsTitle>
								<v8:item>
									<v8:lang>ru</v8:lang>
									<v8:content>Общее отклонение за период</v8:content>
								</v8:item>
							</dcsset:lwsTitle>
							<dcsset:item xsi:type="dcsset:SelectedItemField">
								<dcsset:field>КоличествоОтклонение</dcsset:field>
								<dcsset:lwsTitle>
									<v8:item>
										<v8:lang>ru</v8:lang>
										<v8:content>Количество</v8:content>
									</v8:item>
								</dcsset:lwsTitle>
							</dcsset:item>
							<dcsset:item xsi:type="dcsset:SelectedItemField">
								<dcsset:field>СуммаОтклонение</dcsset:field>
								<dcsset:lwsTitle>
									<v8:item>
										<v8:lang>ru</v8:lang>
										<v8:content>Сумма</v8:content>
									</v8:item>
								</dcsset:lwsTitle>
							</dcsset:item>
							<dcsset:placement>Auto</dcsset:placement>
						</dcsset:item>
					</dcsset:selection>
				</dcsset:column>
				<dcsset:row>
					<dcsset:groupItems>
						<dcsset:item xsi:type="dcsset:GroupItemField">
							<dcsset:field>КлючСтроки</dcsset:field>
							<dcsset:groupType>Hierarchy</dcsset:groupType>
							<dcsset:periodAdditionType>None</dcsset:periodAdditionType>
							<dcsset:periodAdditionBegin xsi:type="xs:dateTime">0001-01-01T00:00:00</dcsset:periodAdditionBegin>
							<dcsset:periodAdditionEnd xsi:type="xs:dateTime">0001-01-01T00:00:00</dcsset:periodAdditionEnd>
						</dcsset:item>
						<dcsset:item xsi:type="dcsset:GroupItemField">
							<dcsset:field>ВидРаботы</dcsset:field>
							<dcsset:groupType>Items</dcsset:groupType>
							<dcsset:periodAdditionType>None</dcsset:periodAdditionType>
							<dcsset:periodAdditionBegin xsi:type="xs:dateTime">0001-01-01T00:00:00</dcsset:periodAdditionBegin>
							<dcsset:periodAdditionEnd xsi:type="xs:dateTime">0001-01-01T00:00:00</dcsset:periodAdditionEnd>
						</dcsset:item>
					</dcsset:groupItems>
					<dcsset:order>
						<dcsset:item xsi:type="dcsset:OrderItemAuto"/>
					</dcsset:order>
					<dcsset:selection>
						<dcsset:item xsi:type="dcsset:SelectedItemAuto"/>
					</dcsset:selection>
					<dcsset:item>
						<dcsset:groupItems>
							<dcsset:item xsi:type="dcsset:GroupItemField">
								<dcsset:field>Ресурс</dcsset:field>
								<dcsset:groupType>Items</dcsset:groupType>
								<dcsset:periodAdditionType>None</dcsset:periodAdditionType>
								<dcsset:periodAdditionBegin xsi:type="xs:dateTime">0001-01-01T00:00:00</dcsset:periodAdditionBegin>
								<dcsset:periodAdditionEnd xsi:type="xs:dateTime">0001-01-01T00:00:00</dcsset:periodAdditionEnd>
							</dcsset:item>
							<dcsset:item xsi:type="dcsset:GroupItemField">
								<dcsset:field>Ресурс.ЕдиницаИзмерения</dcsset:field>
								<dcsset:groupType>Items</dcsset:groupType>
								<dcsset:periodAdditionType>None</dcsset:periodAdditionType>
								<dcsset:periodAdditionBegin xsi:type="xs:dateTime">0001-01-01T00:00:00</dcsset:periodAdditionBegin>
								<dcsset:periodAdditionEnd xsi:type="xs:dateTime">0001-01-01T00:00:00</dcsset:periodAdditionEnd>
							</dcsset:item>
						</dcsset:groupItems>
						<dcsset:order>
							<dcsset:item xsi:type="dcsset:OrderItemAuto"/>
						</dcsset:order>
						<dcsset:selection>
							<dcsset:item xsi:type="dcsset:SelectedItemAuto"/>
						</dcsset:selection>
						<dcsset:outputParameters>
							<dcscor:item xsi:type="dcsset:SettingsParameterValue">
								<dcscor:parameter>РасположениеРеквизитов</dcscor:parameter>
								<dcscor:value xsi:type="dcsset:DataCompositionAttributesPlacement">SpecialPosition</dcscor:value>
							</dcscor:item>
						</dcsset:outputParameters>
					</dcsset:item>
				</dcsset:row>
			</dcsset:item>
		</dcsset:settings>
	</settingsVariant>
</DataCompositionSchema>